odoo/addons/repair_picking_after_done/README.rst
odoo/addons/repair_picking_after_done/__init__.py
odoo/addons/repair_picking_after_done/__manifest__.py
odoo/addons/repair_picking_after_done/i18n/es.po
odoo/addons/repair_picking_after_done/i18n/it.po
odoo/addons/repair_picking_after_done/i18n/repair_picking_after_done.pot
odoo/addons/repair_picking_after_done/migration/14.0.1.0.2/pre-migration.py
odoo/addons/repair_picking_after_done/models/__init__.py
odoo/addons/repair_picking_after_done/models/repair.py
odoo/addons/repair_picking_after_done/readme/CONFIGURE.rst
odoo/addons/repair_picking_after_done/readme/CONTRIBUTORS.rst
odoo/addons/repair_picking_after_done/readme/DESCRIPTION.rst
odoo/addons/repair_picking_after_done/readme/ROADMAP.rst
odoo/addons/repair_picking_after_done/readme/USAGE.rst
odoo/addons/repair_picking_after_done/security/ir.model.access.csv
odoo/addons/repair_picking_after_done/static/description/icon.png
odoo/addons/repair_picking_after_done/static/description/index.html
odoo/addons/repair_picking_after_done/tests/__init__.py
odoo/addons/repair_picking_after_done/tests/test_repair_transfers.py
odoo/addons/repair_picking_after_done/views/repair.xml
odoo/addons/repair_picking_after_done/wizards/__init__.py
odoo/addons/repair_picking_after_done/wizards/repair_move_transfer.py
odoo/addons/repair_picking_after_done/wizards/repair_move_transfer_views.xml
odoo14_addon_repair_picking_after_done-14.0.1.0.3.dev3.dist-info/METADATA
odoo14_addon_repair_picking_after_done-14.0.1.0.3.dev3.dist-info/WHEEL
odoo14_addon_repair_picking_after_done-14.0.1.0.3.dev3.dist-info/top_level.txt
odoo14_addon_repair_picking_after_done-14.0.1.0.3.dev3.dist-info/RECORD
