Metadata-Version: 2.1
Name: odoo14-addon-repair_picking_after_done
Version: 14.0.1.0.3.dev3
Summary: Transfer repaired move to another location directly from repaire order
Home-page: https://github.com/OCA/manufacture
Author: ForgeFlow, Odoo Community Association (OCA)
Author-email: support@odoo-community.org
License: AGPL-3
Classifier: Programming Language :: Python
Classifier: Framework :: Odoo
Classifier: Framework :: Odoo :: 14.0
Classifier: License :: OSI Approved :: GNU Affero General Public License v3
Classifier: Development Status :: 3 - Alpha
Requires-Python: >=3.6
Requires-Dist: odoo14-addon-repair-stock
Requires-Dist: odoo14-addon-repair-type
Requires-Dist: odoo <14.1dev,>=14.0a
